agvis/__init__.py
agvis/__main__.py
agvis/_version.py
agvis/cli.py
agvis/flask_configurations.py
agvis/main.py
agvis/web.py
agvis/cases/ACTIVSg2000.xlsx
agvis/cases/NA.xlsx
agvis/cases/ei528.xlsx
agvis/cases/ercot276.xlsx
agvis/cases/ieee39.xlsx
agvis/cases/maritime_gas.xlsx
agvis/cases/npcc.xlsx
agvis/cases/wecc.xlsx
tests/__init__.py
tests/_test_dime_client.py
tests/conftest.py
tests/test_cli.py
tests/test_web.py
agvis-4.0.0.dist-info/LICENSE
agvis-4.0.0.dist-info/METADATA
agvis-4.0.0.dist-info/WHEEL
agvis-4.0.0.dist-info/entry_points.txt
agvis-4.0.0.dist-info/top_level.txt
agvis-4.0.0.dist-info/RECORD
