Metadata-Version: 2.1
Name: agvis
Version: 4.0.0
Summary: Web application of geographical visualizer for energy systems
Home-page: https://github.com/CURENT/agvis
Author: Nicholas West, Nicholas Parsly, Jinning Wang
Author-email: jinninggm@gmail.com
License: GNU Public License v3
Classifier: Development Status :: 4 - Beta
Classifier: Natural Language :: English
Classifier: Programming Language :: Python :: 3
Classifier: License :: OSI Approved :: GNU General Public License v3 or later (GPLv3+)
Classifier: Environment :: Console
License-File: LICENSE
Requires-Dist: numpy
Requires-Dist: andes
Requires-Dist: dime-client
Requires-Dist: flask
Requires-Dist: gunicorn
Requires-Dist: requests
Requires-Dist: pytest
Requires-Dist: pytest-flask
Requires-Dist: lxml[html_clean]
Provides-Extra: all
Requires-Dist: pydata-sphinx-theme ; extra == 'all'
Requires-Dist: myst-parser ==0.15.2 ; extra == 'all'
Requires-Dist: sphinx ; extra == 'all'
Requires-Dist: numpydoc ; extra == 'all'
Requires-Dist: flake8 ; extra == 'all'
Requires-Dist: sphinx-panels ; extra == 'all'
Requires-Dist: ipython ; extra == 'all'
Requires-Dist: myst-nb ==0.13.2 ; extra == 'all'
Requires-Dist: sphinx-copybutton ; extra == 'all'
Provides-Extra: dev
Requires-Dist: pydata-sphinx-theme ; extra == 'dev'
Requires-Dist: myst-parser ==0.15.2 ; extra == 'dev'
Requires-Dist: sphinx ; extra == 'dev'
Requires-Dist: numpydoc ; extra == 'dev'
Requires-Dist: flake8 ; extra == 'dev'
Requires-Dist: sphinx-panels ; extra == 'dev'
Requires-Dist: ipython ; extra == 'dev'
Requires-Dist: myst-nb ==0.13.2 ; extra == 'dev'
Requires-Dist: sphinx-copybutton ; extra == 'dev'
Provides-Extra: doc
Requires-Dist: pydata-sphinx-theme ; extra == 'doc'
Requires-Dist: myst-parser ==0.15.2 ; extra == 'doc'
Requires-Dist: sphinx ; extra == 'doc'
Requires-Dist: numpydoc ; extra == 'doc'
Requires-Dist: sphinx-panels ; extra == 'doc'
Requires-Dist: myst-nb ==0.13.2 ; extra == 'doc'
Requires-Dist: sphinx-copybutton ; extra == 'doc'
Provides-Extra: flake8
Requires-Dist: flake8 ; extra == 'flake8'
Provides-Extra: ipython
Requires-Dist: ipython ; extra == 'ipython'
Provides-Extra: myst-nb
Requires-Dist: myst-nb ==0.13.2 ; extra == 'myst-nb'
Provides-Extra: myst-parser
Requires-Dist: myst-parser ==0.15.2 ; extra == 'myst-parser'
Provides-Extra: numpydoc
Requires-Dist: numpydoc ; extra == 'numpydoc'
Provides-Extra: pydata-sphinx-theme
Requires-Dist: pydata-sphinx-theme ; extra == 'pydata-sphinx-theme'
Provides-Extra: sphinx
Requires-Dist: sphinx ; extra == 'sphinx'
Provides-Extra: sphinx-copybutton
Requires-Dist: sphinx-copybutton ; extra == 'sphinx-copybutton'
Provides-Extra: sphinx-panels
Requires-Dist: sphinx-panels ; extra == 'sphinx-panels'
